<form headerdensity="HighWithControls">
    <hiddencontrols>
        <data id="isprimary" datafieldname="isprimary" classid="{5546E6CD-394C-4bee-94A8-4425E17EF6C6}" />
        <data id="parentarticlecontentid" datafieldname="parentarticlecontentid" classid="{5546E6CD-394C-4bee-94A8-4425E17EF6C6}" />
        <data id="articlepublicnumber" datafieldname="articlepublicnumber" classid="{5546E6CD-394C-4bee-94A8-4425E17EF6C6}" />
        <data id="statecode" datafieldname="statecode" classid="{5546E6CD-394C-4bee-94A8-4425E17EF6C6}" />
        <data id="majorversionnumber" datafieldname="majorversionnumber" classid="{5546E6CD-394C-4bee-94A8-4425E17EF6C6}" />
        <data id="minorversionnumber" datafieldname="minorversionnumber" classid="{5546E6CD-394C-4bee-94A8-4425E17EF6C6}" />
        <data id="primaryauthorid" datafieldname="primaryauthorid" classid="{270BD3DB-D9AF-4782-9025-509E298DEC0A}" />
        <data id="languagelocaleid" datafieldname="languagelocaleid" classid="{270BD3DB-D9AF-4782-9025-509E298DEC0A}" />
        <data id="publishon" datafieldname="publishon" classid="{5B773807-9FB2-42db-97C3-7A91EFF8ADFF}" />
        <data id="expirationdate" datafieldname="expirationdate" classid="{5B773807-9FB2-42db-97C3-7A91EFF8ADFF}" />
        <data id="expiredreviewoptions" datafieldname="expiredreviewoptions" classid="{5546E6CD-394C-4bee-94A8-4425E17EF6C6}" />
        <data id="isinternal" datafieldname="isinternal" classid="{5546E6CD-394C-4bee-94A8-4425E17EF6C6}" />
    </hiddencontrols>
    <tabs>
        <tab id="{790c584c-6fac-4509-b26a-8b49d3be96de}" IsUserDefined="0" name="general" expanded="true" locklevel="0" showlabel="true">
            <labels>
                <label description="Content" languagecode="1033" />
            </labels>
            <columns>
                <column width="100%">
                    <sections>
                        <section id="{cfb63827-3c0b-4138-a6e8-59f0f2e3ef1f}" showlabel="true" showbar="false" IsUserDefined="0" name="Knowledge Information" layout="varwidth" columns="11" labelwidth="115" celllabelalignment="Left" celllabelposition="Left">
                            <labels>
                                <label description="ARTICLE CONTENT" languagecode="1033" />
                            </labels>
                            <rows>
                                <row>
                                    <cell auto="false" showlabel="true" locklevel="0" rowspan="1" id="{7c61e6c8-dfca-489f-837d-3966de3d4f74}">
                                        <labels>
                                            <label description="Title" languagecode="1033" />
                                        </labels>
                                        <control id="title" datafieldname="title" classid="{4273EDBD-AC1D-40d3-9FB2-095C621B552D}" />
                                    </cell>
                                    <cell auto="false" showlabel="true" locklevel="0" rowspan="1" id="{83ebbc25-7efe-47c3-b2eb-60d063234fc6}">
                                        <labels>
                                            <label description="Description" languagecode="1033" />
                                        </labels>
                                        <control id="description" datafieldname="description" classid="{E0DECE4B-6FC8-4a8f-A065-082708572369}" />
                                    </cell>
                                </row>
                                <row>
                                    <cell auto="false" showlabel="true" locklevel="0" rowspan="1" id="{ea7f052a-9992-4be9-b9df-a9c8f50c0754}">
                                        <labels>
                                            <label description="Keywords" languagecode="1033" />
                                        </labels>
                                        <control id="keywords" datafieldname="keywords" classid="{E0DECE4B-6FC8-4a8f-A065-082708572369}" disabled="false" />
                                    </cell>
                                    <cell id="{d1b3dec8-2315-43e4-9c10-f46dde758e97}">
                                        <labels>
                                            <label description="" languagecode="1033" />
                                        </labels>
                                    </cell>
                                </row>
                            </rows>
                        </section>
                        <section id="{2AEFF681-0897-4BF0-806A-C46EC0A89A36}" showlabel="true" showbar="false" IsUserDefined="0" name="Content" layout="varwidth" columns="1" labelwidth="115" celllabelalignment="Left" celllabelposition="Left">
                            <labels>
                                <label description="CONTENT" languagecode="1033" />
                            </labels>
                            <rows>
                                <row>
                                    <cell id="{d4d814ab-13be-0184-0d15-b9e611213e88}" showlabel="false" colspan="1" auto="false" rowspan="1">
                                        <labels>
                                            <label description="AllowedOriginsDisclaimer" languagecode="1033" />
                                        </labels>
                                        <control id="webResource_allowed_origins_disclaimer" classid="{9FDF5F91-88B1-47f4-AD53-C11EFC01A01D}">
                                            <parameters>
                                                <Url>msdyn_KMAllowedOriginsInfo.html</Url>
                                                <PassParameters>false</PassParameters>
                                                <Security>false</Security>
                                                <Scrolling>auto</Scrolling>
                                                <Border>false</Border>
                                                <ShowOnMobileClient>false</ShowOnMobileClient>
                                                <WebResourceId>{500C3625-C70F-EC11-94F9-000D3AFBA325}</WebResourceId>
                                            </parameters>
                                        </control>
                                        <events>
                                            <event name="onload" application="false">
                                                <dependencies />
                                            </event>
                                        </events>
                                    </cell>
                                </row>
                                <row>
                                    <cell auto="false" showlabel="false" locklevel="0" rowspan="12" id="{dbfa4f73-aabf-4c45-87d9-e698801c91ae}">
                                        <labels>
                                            <label description="Content" languagecode="1033" />
                                        </labels>
                                        <control id="content" classid="{F9A8A302-114E-466A-B582-6771B2AE0D92}" datafieldname="content" disabled="false" uniqueid="{E7328698-05C1-7D5D-435C-754E27197E75}" />
                                    </cell>
                                </row>
                                <row />
                                <row />
                                <row />
                                <row />
                                <row />
                                <row />
                                <row />
                                <row />
                                <row />
                                <row />
                                <row />
                            </rows>
                        </section>
                    </sections>
                </column>
            </columns>
        </tab>
        <tab name="summary" verticallayout="true" id="{8e44337a-3b85-4b81-a541-520c139e1d90}" visible="true" expanded="true" IsUserDefined="0" showlabel="true">
            <labels>
                <label description="Summary" languagecode="1033" />
            </labels>
            <columns>
                <column width="33%">
                    <sections>
                        <section id="{b705aea2-6465-4c00-b6cc-ae84840e86ae}" showlabel="true" showbar="false" IsUserDefined="0" name="Portal Settings" layout="varwidth" columns="1" labelwidth="115" celllabelalignment="Left" celllabelposition="Left">
                            <labels>
                                <label description="BASIC SETTINGS" languagecode="1033" />
                            </labels>
                            <rows>
                                <row>
                                    <cell auto="false" showlabel="true" rowspan="1" colspan="1" id="{ff5fddf0-f324-462f-8f1c-878f36ddadc9}">
                                        <labels>
                                            <label description="Internal" languagecode="1033" />
                                        </labels>
                                        <control id="isinternal" datafieldname="isinternal" classid="{3EF39988-22BB-4f0b-BBBE-64B5A3748AEE}" disabled="false" />
                                    </cell>
                                </row>
                                <row>
                                    <cell id="{03469958-0928-447f-b924-e84cb96d3be6}" showlabel="true" locklevel="0" rowspan="1" colspan="1">
                                        <labels>
                                            <label description="Status Reason" languagecode="1033" />
                                        </labels>
                                        <control id="statuscode" classid="{5D68B988-0661-4db2-BC3E-17598AD3BE6C}" datafieldname="statuscode" disabled="false" />
                                    </cell>
                                </row>
                                <row>
                                    <cell auto="false" showlabel="true" locklevel="0" rowspan="1" colspan="1" id="{742236ab-f4bc-4527-b7da-08712106b31f}">
                                        <labels>
                                            <label description="Owner" languagecode="1033" />
                                        </labels>
                                        <control id="ownerid" datafieldname="ownerid" classid="{270BD3DB-D9AF-4782-9025-509E298DEC0A}" />
                                    </cell>
                                </row>
                                <row>
                                    <cell auto="false" showlabel="true" locklevel="0" rowspan="1" colspan="1" id="{34f612cb-47eb-4cbd-afe5-846d5423a4c4}">
                                        <labels>
                                            <label description="Article Public Number" languagecode="1033" />
                                        </labels>
                                        <control id="articlepublicnumber" datafieldname="articlepublicnumber" classid="{4273EDBD-AC1D-40d3-9FB2-095C621B552D}" disabled="true" />
                                    </cell>
                                </row>
                                <row>
                                    <cell id="{bd3c0f15-c14c-4cb6-97e2-838242ab4990}" showlabel="true" locklevel="0" labelid="{75c343d8-d0a2-411f-85f7-72edb60bec55}">
                                        <labels>
                                            <label description="Primary Author Id" languagecode="1033" />
                                        </labels>
                                        <control id="primaryauthorid" datafieldname="primaryauthorid" classid="{270BD3DB-D9AF-4782-9025-509E298DEC0A}" />
                                    </cell>
                                </row>
                                <row>
                                    <cell id="{9481eaf2-7f88-4ee5-b78e-e4cf289da1ea}" showlabel="true" locklevel="0">
                                        <labels>
                                            <label description="Language" languagecode="1033" />
                                        </labels>
                                        <control id="languagelocaleid" classid="{270BD3DB-D9AF-4782-9025-509E298DEC0A}" datafieldname="languagelocaleid" disabled="true" />
                                    </cell>
                                </row>
                                <row>
                                    <cell id="{510ad14b-bbd5-417e-bee7-44d1778a94d8}" showlabel="true" locklevel="0">
                                        <labels>
                                            <label description="Major Version Number" languagecode="1033" />
                                        </labels>
                                        <control id="header_majorversionnumber" classid="{C6D124CA-7EDA-4a60-AEA9-7FB8D318B68F}" datafieldname="majorversionnumber" disabled="true" />
                                    </cell>
                                </row>
                                <row>
                                    <cell id="{559a92d6-fbba-41dd-a640-f01673670ffd}" showlabel="true" locklevel="0">
                                        <labels>
                                            <label description="Minor Version Number" languagecode="1033" />
                                        </labels>
                                        <control id="header_minorversionnumber" classid="{C6D124CA-7EDA-4a60-AEA9-7FB8D318B68F}" datafieldname="minorversionnumber" disabled="true" />
                                    </cell>
                                </row>
                                <row>
                                    <cell auto="false" showlabel="true" locklevel="0" rowspan="1" colspan="1" id="{b68d033a-dfc8-45b4-bdf3-5de3028afc3b}">
                                        <labels>
                                            <label description="Created By" languagecode="1033" />
                                        </labels>
                                        <control id="createdname" datafieldname="createdby" classid="{270BD3DB-D9AF-4782-9025-509E298DEC0A}" disabled="true" />
                                    </cell>
                                </row>
                                <row>
                                    <cell auto="false" showlabel="true" locklevel="0" rowspan="1" colspan="1" id="{bf6a26c7-a57a-41df-b5af-cff4fc7fc404}">
                                        <labels>
                                            <label description="Created On" languagecode="1033" />
                                        </labels>
                                        <control id="creadedon" datafieldname="createdon" classid="{5B773807-9FB2-42db-97C3-7A91EFF8ADFF}" disabled="true" />
                                    </cell>
                                </row>
                                <row>
                                    <cell auto="false" showlabel="true" locklevel="0" rowspan="1" colspan="1" id="{c0b99a48-48cb-476b-b4a1-8074867078b4}">
                                        <labels>
                                            <label description="Modified By" languagecode="1033" />
                                        </labels>
                                        <control id="modifiedname" datafieldname="modifiedby" classid="{270BD3DB-D9AF-4782-9025-509E298DEC0A}" disabled="true" />
                                    </cell>
                                </row>
                                <row>
                                    <cell auto="false" showlabel="true" locklevel="0" rowspan="1" colspan="1" id="{960102b9-a96b-45d8-a05c-842c50cd2842}">
                                        <labels>
                                            <label description="Modified On" languagecode="1033" />
                                        </labels>
                                        <control id="modifiedon" datafieldname="modifiedon" classid="{5B773807-9FB2-42db-97C3-7A91EFF8ADFF}" disabled="true" />
                                    </cell>
                                </row>
                                <row>
                                    <cell id="{db4c6695-5062-4bbf-8144-7a4a8864adc6}" locklevel="0" colspan="1" rowspan="1">
                                        <labels>
                                            <label description="Agent Review Status" languagecode="1033" />
                                        </labels>
                                        <control id="msdyn_agentreviewstatus" classid="{3EF39988-22BB-4F0B-BBBE-64B5A3748AEE}" datafieldname="msdyn_agentreviewstatus" disabled="false" />
                                    </cell>
                                </row>
                                <row>
                                    <cell id="{aeb950c6-26ce-4734-ae89-cc246d0b60a6}" locklevel="0" colspan="1" rowspan="1">
                                        <labels>
                                            <label description="Compliance State" languagecode="1033" />
                                        </labels>
                                        <control id="msdyn_compliancestatecode" classid="{3EF39988-22BB-4F0B-BBBE-64B5A3748AEE}" datafieldname="msdyn_compliancestatecode" disabled="false" />
                                    </cell>
                                </row>
                            </rows>
                        </section>
                        <section id="{66ce1647-a59e-4393-9d14-d3437375266b}" showlabel="true" showbar="false" IsUserDefined="0" name="Publish Settings" layout="varwidth" columns="1" labelwidth="115" celllabelalignment="Left" celllabelposition="Left">
                            <labels>
                                <label description="PUBLISH SETTINGS" languagecode="1033" />
                            </labels>
                            <rows>
                                <row>
                                    <cell id="{f1d1842b-901c-4a1b-ab64-fab6fe8736a2}" userspacer="0">
                                        <labels>
                                            <label description="Subject" languagecode="1033" />
                                        </labels>
                                        <control id="subjectid" classid="{270BD3DB-D9AF-4782-9025-509E298DEC0A}" datafieldname="subjectid" />
                                    </cell>
                                </row>
                                <row>
                                    <cell auto="false" showlabel="true" locklevel="0" rowspan="1" colspan="1" id="{a801bd58-0281-4de6-a2af-d1ca48cf5459}">
                                        <labels>
                                            <label description="Publish On" languagecode="1033" />
                                        </labels>
                                        <control id="publishon" datafieldname="publishon" classid="{5B773807-9FB2-42db-97C3-7A91EFF8ADFF}" disabled="false" />
                                    </cell>
                                </row>
                                <row>
                                    <cell auto="false" showlabel="true" locklevel="0" rowspan="1" colspan="1" id="{475d0f03-23a8-4a88-b01c-bd725a76cda0}">
                                        <labels>
                                            <label description="Expiration Date" languagecode="1033" />
                                        </labels>
                                        <control id="expirationdate" datafieldname="expirationdate" classid="{5B773807-9FB2-42db-97C3-7A91EFF8ADFF}" disabled="false" />
                                    </cell>
                                </row>
                            </rows>
                        </section>
                    </sections>
                </column>
                <column width="33%">
                    <sections>
                        <section name="Timeline" showlabel="true" showbar="false" locklevel="0" id="{1db3722e-e014-4591-891d-36d3ab68f4ed}" IsUserDefined="0" layout="varwidth" columns="1" labelwidth="115" celllabelalignment="Left" celllabelposition="Left">
                            <labels>
                                <label description="TIMELINE" languagecode="1033" />
                            </labels>
                            <rows>
                                <row>
                                    <cell id="{5f835b01-a1e7-4471-aedd-a48c7bfc26c7}" colspan="1" rowspan="20" showlabel="false" locklevel="0">
                                        <labels>
                                            <label description="" languagecode="1033" />
                                        </labels>
                                        <control id="notescontrol" classid="{06375649-c143-495e-a496-c962e5b4488e}" disabled="false" />
                                    </cell>
                                </row>
                                <row />
                                <row />
                                <row />
                                <row />
                                <row />
                                <row />
                                <row />
                                <row />
                                <row />
                                <row />
                                <row />
                                <row />
                                <row />
                                <row />
                                <row />
                                <row />
                                <row />
                                <row />
                                <row />
                            </rows>
                        </section>
                    </sections>
                </column>
                <column width="34%">
                    <sections>
                        <section name="ref_pan_Related" id="{f7e1553e-2baf-4cae-899d-91a728bb4f6d}" showlabel="true" showbar="false" IsUserDefined="0" layout="varwidth" columns="1" labelwidth="115" celllabelalignment="Left" celllabelposition="Left">
                            <labels>
                                <label description="RELATED INFORMATION" languagecode="1033" />
                            </labels>
                            <rows>
                                <row>
                                    <cell id="{f12aad0c-5c5f-48c4-98e4-afd3dc03d68c}" colspan="1" showlabel="false">
                                        <labels>
                                            <label description="Related Versions" languagecode="1033" />
                                        </labels>
                                        <control id="relatedversionsquickform" classid="{B68B05F0-A46D-43F8-843B-917920AF806A}" datafieldname="parentarticlecontentid" disabled="false">
                                            <parameters>
                                                <QuickForms>&lt;QuickFormIds&gt;&lt;QuickFormId entityname="knowledgearticle"&gt;53C74C18-823C-4D38-8F58-649252DA6835&lt;/QuickFormId&gt;&lt;/QuickFormIds&gt;</QuickForms>
                                                <ControlMode>Edit</ControlMode>
                                                <ReferencePanelQuickFormCollectionIconUrl>/_imgs/KnowledgeArticle/Versions_16.png</ReferencePanelQuickFormCollectionIconUrl>
                                            </parameters>
                                        </control>
                                    </cell>
                                </row>
                                <row>
                                    <cell id="{945eba3b-32ea-4dde-948e-eb7f4100bff8}" showlabel="true" colspan="1">
                                        <labels>
                                            <label description="Related Translations" languagecode="1033" />
                                        </labels>
                                        <control id="RelatedTranslationsGrid" classid="{F9A8A302-114E-466A-B582-6771B2AE0D92}" uniqueid="{216CE061-1BD8-BE44-6786-B4EA9898527D}">
                                            <parameters>
                                                <ViewId>{ae82a232-1529-4bde-9972-93ce21a095c6}</ViewId>
                                                <RelationshipName>knowledgearticle_parentarticle_contentid</RelationshipName>
                                                <TargetEntityType>knowledgearticle</TargetEntityType>
                                                <AutoExpand>Auto</AutoExpand>
                                                <EnableQuickFind>false</EnableQuickFind>
                                                <EnableViewPicker>false</EnableViewPicker>
                                                <EnableJumpBar>false</EnableJumpBar>
                                                <ChartGridMode>Grid</ChartGridMode>
                                                <EnableChartPicker>false</EnableChartPicker>
                                                <RecordsPerPage>5</RecordsPerPage>
                                                <EnableContextualActions>true</EnableContextualActions>
                                                <ReferencePanelSubgridIconUrl>/_imgs/KnowledgeArticle/Language_16.png</ReferencePanelSubgridIconUrl>
                                            </parameters>
                                        </control>
                                    </cell>
                                </row>
                                <row>
                                    <cell id="{da1d5090-dce2-4b5b-a6c5-5e0665540f83}" showlabel="true" colspan="1">
                                        <labels>
                                            <label description="Related Categories" languagecode="1033" />
                                        </labels>
                                        <control id="RelatedCategoriesGrid" classid="{02D4264B-47E2-4B4C-AA95-F439F3F4D458}">
                                            <parameters>
                                                <ViewId>{50E935BA-2E0D-460D-AD36-B699B9B991D8}</ViewId>
                                                <RelationshipName>knowledgearticle_category</RelationshipName>
                                                <TargetEntityType>category</TargetEntityType>
                                                <AutoExpand>Fixed</AutoExpand>
                                                <EnableQuickFind>false</EnableQuickFind>
                                                <EnableViewPicker>false</EnableViewPicker>
                                                <EnableJumpBar>false</EnableJumpBar>
                                                <ChartGridMode>Grid</ChartGridMode>
                                                <EnableChartPicker>false</EnableChartPicker>
                                                <RecordsPerPage>5</RecordsPerPage>
                                                <EnableContextualActions>true</EnableContextualActions>
                                                <ReferencePanelSubgridIconUrl>/_imgs/KnowledgeArticle/Hierarchy_16.png</ReferencePanelSubgridIconUrl>
                                            </parameters>
                                        </control>
                                    </cell>
                                </row>
                                <row>
                                    <cell id="{4d82f200-9aa9-4de6-80e0-3dd0f43ea3d9}" colspan="1" showlabel="false">
                                        <labels>
                                            <label description="Related Articles" languagecode="1033" />
                                        </labels>
                                        <control id="relatedarticlequickform" classid="{B68B05F0-A46D-43F8-843B-917920AF806A}" datafieldname="rootarticleid" disabled="false">
                                            <parameters>
                                                <QuickForms>&lt;QuickFormIds&gt;&lt;QuickFormId entityname="knowledgearticle"&gt;cb6b2f21-b844-4192-8561-b285f2708d08&lt;/QuickFormId&gt;&lt;/QuickFormIds&gt;</QuickForms>
                                                <ControlMode>Edit</ControlMode>
                                                <ReferencePanelQuickFormCollectionIconUrl>/_imgs/KnowledgeArticle/RelatedArticles_16.png</ReferencePanelQuickFormCollectionIconUrl>
                                            </parameters>
                                        </control>
                                    </cell>
                                </row>
                                <row>
                                    <cell id="{d5be9500-d728-2ade-012d-eb8c6a23476d}" showlabel="true" colspan="1" auto="false" rowspan="7">
                                        <labels>
                                            <label description="Related Work Orders" languagecode="1033" />
                                        </labels>
                                        <control id="workordersubgrid" classid="{02D4264B-47E2-4B4C-AA95-F439F3F4D458}" uniqueid="{6ad93205-75c0-aaea-4077-69c5eba0ddae}">
                                            <parameters>
                                                <ViewId>{FCE37246-EBA1-4E92-BB9D-F8CB3EC38E3F}</ViewId>
                                                <IsUserView>false</IsUserView>
                                                <RelationshipName>msdyn_msdyn_workorder_knowledgearticle</RelationshipName>
                                                <TargetEntityType>msdyn_workorder</TargetEntityType>
                                                <AutoExpand>Fixed</AutoExpand>
                                                <EnableQuickFind>false</EnableQuickFind>
                                                <EnableViewPicker>false</EnableViewPicker>
                                                <ViewIds>{FCE37246-EBA1-4E92-BB9D-F8CB3EC38E3F}</ViewIds>
                                                <EnableJumpBar>false</EnableJumpBar>
                                                <ChartGridMode>All</ChartGridMode>
                                                <VisualizationId>{8E746648-1A4E-E111-93B3-000C2959F9B8}</VisualizationId>
                                                <IsUserChart>false</IsUserChart>
                                                <EnableChartPicker>true</EnableChartPicker>
                                                <RecordsPerPage>4</RecordsPerPage>
                                                <HeaderColorCode>#F3F3F3</HeaderColorCode>
                                                <RelationshipRoleOrdinal>2</RelationshipRoleOrdinal>
                                                <ReferencePanelSubgridIconUrl>msdyn_/Icons/SVG/WorkOrders.svg</ReferencePanelSubgridIconUrl>
                                            </parameters>
                                        </control>
                                    </cell>
                                </row>
                                <row />
                                <row />
                                <row />
                                <row />
                                <row />
                                <row />
                                <row>
                                    <cell id="{8e598441-c940-3912-7151-e2514393a437}" showlabel="true" colspan="1" auto="false" rowspan="7">
                                        <labels>
                                            <label description="Related Customer Assets" languagecode="1033" />
                                        </labels>
                                        <control id="customerassetsubgrid" classid="{02D4264B-47E2-4B4C-AA95-F439F3F4D458}" uniqueid="{be509208-ae50-089e-c50b-720700348eca}">
                                            <parameters>
                                                <ViewId>{6ECB03A4-ACDA-44AE-83E3-C60BA8338DBB}</ViewId>
                                                <IsUserView>false</IsUserView>
                                                <RelationshipName>msdyn_msdyn_customerasset_knowledgearticle</RelationshipName>
                                                <TargetEntityType>msdyn_customerasset</TargetEntityType>
                                                <AutoExpand>Fixed</AutoExpand>
                                                <EnableQuickFind>false</EnableQuickFind>
                                                <EnableViewPicker>false</EnableViewPicker>
                                                <ViewIds>{6ECB03A4-ACDA-44AE-83E3-C60BA8338DBB}</ViewIds>
                                                <EnableJumpBar>false</EnableJumpBar>
                                                <ChartGridMode>All</ChartGridMode>
                                                <VisualizationId />
                                                <IsUserChart>false</IsUserChart>
                                                <EnableChartPicker>true</EnableChartPicker>
                                                <RecordsPerPage>4</RecordsPerPage>
                                                <HeaderColorCode>#F3F3F3</HeaderColorCode>
                                                <RelationshipRoleOrdinal>2</RelationshipRoleOrdinal>
                                                <ReferencePanelSubgridIconUrl>msdyn_/Icons/SVG/CustomerAssets.svg</ReferencePanelSubgridIconUrl>
                                            </parameters>
                                        </control>
                                    </cell>
                                </row>
                                <row />
                                <row />
                                <row />
                                <row />
                                <row />
                                <row />
                                <row>
                                    <cell id="{c8d67871-4da6-cea1-d76d-279a0d4bcc6d}" showlabel="true" colspan="1" auto="false" rowspan="7">
                                        <labels>
                                            <label description="Related Products" languagecode="1033" />
                                        </labels>
                                        <control id="productsubgrid" classid="{02D4264B-47E2-4B4C-AA95-F439F3F4D458}" uniqueid="{cbb537d8-05e2-4e29-6ce9-39a8da05d98e}">
                                            <parameters>
                                                <ViewId>{CCF8B615-DB4D-E811-8148-000D3A061A01}</ViewId>
                                                <IsUserView>false</IsUserView>
                                                <RelationshipName>msdyn_product_knowledgearticle</RelationshipName>
                                                <TargetEntityType>product</TargetEntityType>
                                                <AutoExpand>Fixed</AutoExpand>
                                                <EnableQuickFind>false</EnableQuickFind>
                                                <EnableViewPicker>false</EnableViewPicker>
                                                <ViewIds>{CCF8B615-DB4D-E811-8148-000D3A061A01}</ViewIds>
                                                <EnableJumpBar>false</EnableJumpBar>
                                                <ChartGridMode>All</ChartGridMode>
                                                <VisualizationId />
                                                <IsUserChart>false</IsUserChart>
                                                <EnableChartPicker>true</EnableChartPicker>
                                                <RecordsPerPage>4</RecordsPerPage>
                                                <HeaderColorCode>#F3F3F3</HeaderColorCode>
                                                <RelationshipRoleOrdinal>2</RelationshipRoleOrdinal>
                                                <ReferencePanelSubgridIconUrl>msdyn_/Icons/SVG/Product.svg</ReferencePanelSubgridIconUrl>
                                            </parameters>
                                        </control>
                                    </cell>
                                </row>
                                <row />
                                <row />
                                <row />
                                <row />
                                <row />
                                <row />
                                <row>
                                    <cell id="{44c3a795-5da4-2895-81b9-72e81a4483ce}" showlabel="true" colspan="1" auto="false" rowspan="7">
                                        <labels>
                                            <label description="Related Incident Types" languagecode="1033" />
                                        </labels>
                                        <control id="incidenttypesubgrid" classid="{02D4264B-47E2-4B4C-AA95-F439F3F4D458}" uniqueid="{3ba84191-5cdb-7bb9-1b7c-761e816c4642}">
                                            <parameters>
                                                <ViewId>{467A8F92-753B-485E-8BA9-13DE8B7CB3A7}</ViewId>
                                                <IsUserView>false</IsUserView>
                                                <RelationshipName>msdyn_msdyn_incidenttype_knowledgearticle</RelationshipName>
                                                <TargetEntityType>msdyn_incidenttype</TargetEntityType>
                                                <AutoExpand>Fixed</AutoExpand>
                                                <EnableQuickFind>false</EnableQuickFind>
                                                <EnableViewPicker>false</EnableViewPicker>
                                                <ViewIds>{467A8F92-753B-485E-8BA9-13DE8B7CB3A7}</ViewIds>
                                                <EnableJumpBar>false</EnableJumpBar>
                                                <ChartGridMode>All</ChartGridMode>
                                                <VisualizationId />
                                                <IsUserChart>false</IsUserChart>
                                                <EnableChartPicker>true</EnableChartPicker>
                                                <RecordsPerPage>4</RecordsPerPage>
                                                <HeaderColorCode>#F3F3F3</HeaderColorCode>
                                                <RelationshipRoleOrdinal>2</RelationshipRoleOrdinal>
                                                <ReferencePanelSubgridIconUrl>msdyn_/Icons/SVG/IncidentTriangle.SVG</ReferencePanelSubgridIconUrl>
                                            </parameters>
                                        </control>
                                    </cell>
                                </row>
                                <row />
                                <row />
                                <row />
                                <row />
                                <row />
                                <row />
                            </rows>
                        </section>
                    </sections>
                </column>
            </columns>
        </tab>
        <tab name="analytics" id="{14030ce7-38e0-4a47-8edd-c62b6a57fa24}" IsUserDefined="0" expanded="true" locklevel="0" showlabel="true">
            <labels>
                <label description="Analytics" languagecode="1033" />
            </labels>
            <columns>
                <column width="33%">
                    <sections>
                        <section id="{699c0a0c-1968-4dbc-95e1-630d71c87a10}" showlabel="true" showbar="false" IsUserDefined="0" name="Views" layout="varwidth" columns="1" labelwidth="115" celllabelalignment="Left" celllabelposition="Left">
                            <labels>
                                <label description="Views" languagecode="1033" />
                            </labels>
                            <rows>
                                <row>
                                    <cell id="{749d0de4-b15a-4aaa-83d4-4cdb7e1d0153}" colspan="1" showlabel="false">
                                        <labels>
                                            <label description="Article View Count" languagecode="1033" />
                                        </labels>
                                        <control id="knowledgearticleviews" classid="{C6D124CA-7EDA-4a60-AEA9-7FB8D318B68F}" datafieldname="knowledgearticleviews" disabled="true" />
                                    </cell>
                                </row>
                                <row>
                                    <cell id="{b0d846b4-dc40-4a9c-8dfd-22a661747d15}" showlabel="true" colspan="1" rowspan="7" auto="false" userspacer="0">
                                        <labels>
                                            <label description="Views by day and location" languagecode="1033" />
                                        </labels>
                                        <control id="KnowledgearticleviewsGrid" classid="{E7A81278-8635-4d9e-8D4D-59480B391C5B}">
                                            <parameters>
                                                <ViewId>{8a34b2e6-d82a-4ccf-a71f-ead4332b3f08}</ViewId>
                                                <RelationshipName>knowledgearticle_views</RelationshipName>
                                                <TargetEntityType>knowledgearticleviews</TargetEntityType>
                                                <AutoExpand>Auto</AutoExpand>
                                                <EnableQuickFind>false</EnableQuickFind>
                                                <EnableViewPicker>false</EnableViewPicker>
                                                <EnableJumpBar>false</EnableJumpBar>
                                                <ChartGridMode>Grid</ChartGridMode>
                                                <EnableChartPicker>false</EnableChartPicker>
                                                <RecordsPerPage>5</RecordsPerPage>
                                                <EnableContextualActions>false</EnableContextualActions>
                                            </parameters>
                                        </control>
                                    </cell>
                                </row>
                                <row />
                                <row />
                                <row />
                                <row />
                                <row />
                                <row />
                            </rows>
                        </section>
                    </sections>
                </column>
                <column width="33%">
                    <sections>
                        <section name="Feedback" showlabel="true" showbar="false" locklevel="0" id="{f9ea8c09-a583-4c53-871d-5642300cbfc6}" IsUserDefined="0" layout="varwidth" columns="1" labelwidth="115" celllabelalignment="Left" celllabelposition="Left">
                            <labels>
                                <label description="Feedback" languagecode="1033" />
                            </labels>
                            <rows>
                                <row>
                                    <cell id="{5b0f68ad-be99-4855-89d3-05a0c311f7bd}" showlabel="true" locklevel="0">
                                        <labels>
                                            <label description="Rating" languagecode="1033" />
                                        </labels>
                                        <control id="rating" classid="{C3EFE0C3-0EC6-42be-8349-CBD9079DFD8E}" datafieldname="rating" disabled="false" />
                                    </cell>
                                </row>
                                <row>
                                    <cell id="{fc34b70b-1747-47f4-b4fa-b60e84fdedd5}" showlabel="true" colspan="1" auto="false" rowspan="6">
                                        <labels>
                                            <label description="Knowledge Articles" languagecode="1033" />
                                        </labels>
                                        <control id="Feedback" classid="{E7A81278-8635-4d9e-8D4D-59480B391C5B}" indicationOfSubgrid="true">
                                            <parameters>
                                                <ViewId>{90f0300e-101a-4462-96af-677cdfd654da}</ViewId>
                                                <IsUserView>false</IsUserView>
                                                <RelationshipName>KnowledgeArticle_Feedback</RelationshipName>
                                                <TargetEntityType>feedback</TargetEntityType>
                                                <AutoExpand>Auto</AutoExpand>
                                                <EnableQuickFind>false</EnableQuickFind>
                                                <EnableViewPicker>false</EnableViewPicker>
                                                <ViewIds />
                                                <EnableJumpBar>false</EnableJumpBar>
                                                <ChartGridMode>Grid</ChartGridMode>
                                                <VisualizationId />
                                                <IsUserChart>false</IsUserChart>
                                                <EnableChartPicker>false</EnableChartPicker>
                                                <RecordsPerPage>4</RecordsPerPage>
                                            </parameters>
                                        </control>
                                    </cell>
                                </row>
                                <row />
                                <row />
                                <row />
                                <row />
                                <row />
                            </rows>
                        </section>
                    </sections>
                </column>
                <column width="33%">
                    <sections>
                        <section id="{6fbbc469-9826-46b3-af16-b0a05270a4fc}" showlabel="true" showbar="false" IsUserDefined="0" name="Cases" layout="varwidth" columns="1" labelwidth="115" celllabelalignment="Left" celllabelposition="Left">
                            <labels>
                                <label description="Cases" languagecode="1033" />
                            </labels>
                            <rows>
                                <row>
                                    <cell id="{baeccbd6-ac81-4dce-9a08-de33b8f06da5}" showlabel="true" colspan="1" rowspan="7" auto="false" userspacer="0">
                                        <labels>
                                            <label description="Cases using this article" languagecode="1033" />
                                        </labels>
                                        <control id="RelatedCasesGrid" classid="{E7A81278-8635-4d9e-8D4D-59480B391C5B}">
                                            <parameters>
                                                <ViewId>{d4af3595-52f5-43a4-b89c-47a413f27665}</ViewId>
                                                <RelationshipName>incident_knowledgearticles</RelationshipName>
                                                <TargetEntityType>knowledgearticleincident</TargetEntityType>
                                                <AutoExpand>Auto</AutoExpand>
                                                <EnableQuickFind>false</EnableQuickFind>
                                                <EnableViewPicker>false</EnableViewPicker>
                                                <EnableJumpBar>false</EnableJumpBar>
                                                <ChartGridMode>Grid</ChartGridMode>
                                                <EnableChartPicker>false</EnableChartPicker>
                                                <RecordsPerPage>5</RecordsPerPage>
                                                <EnableContextualActions>false</EnableContextualActions>
                                            </parameters>
                                        </control>
                                    </cell>
                                </row>
                                <row />
                                <row />
                                <row />
                                <row />
                                <row />
                                <row />
                            </rows>
                        </section>
                    </sections>
                </column>
            </columns>
        </tab>
    </tabs>
    <header id="{094c8b53-dff1-40aa-b8a9-16dd18c8160f}" columns="1111" celllabelposition="Top" labelwidth="115">
        <rows>
            <row>
                <cell id="{4a417498-e5c9-4bc8-afb3-ef77d2706a69}" showlabel="true" locklevel="0">
                    <labels>
                        <label description="Language" languagecode="1033" />
                    </labels>
                    <control id="header_languagelocaleid" classid="{270BD3DB-D9AF-4782-9025-509E298DEC0A}" datafieldname="languagelocaleid" disabled="true" />
                </cell>
                <cell id="{b6795464-6c6b-475b-b950-330cccc4b9c0}" showlabel="true" locklevel="0">
                    <labels>
                        <label description="Status Reason" languagecode="1033" />
                    </labels>
                    <control id="header_statuscode" classid="{5D68B988-0661-4db2-BC3E-17598AD3BE6C}" datafieldname="statuscode" disabled="false" />
                </cell>
                <cell id="{80fed207-95f5-4308-9c0e-4d77720daa82}">
                    <labels>
                        <label description="" languagecode="1033" />
                    </labels>
                </cell>
                <cell id="{c8906ff2-769a-44d5-889f-102c06005527}">
                    <labels>
                        <label description="" languagecode="1033" />
                    </labels>
                </cell>
            </row>
        </rows>
    </header>
    <footer id="{B21F9D32-C495-4D3A-BF5D-BF2B8A332CDC}">
        <rows>
            <row>
                <cell id="{92cdeb45-94cc-c487-d928-db1731363caa}" showlabel="true" locklevel="0">
                    <labels>
                        <label description="Major Version Number" languagecode="1033" />
                    </labels>
                    <control id="header_majorversionnumber" classid="{C6D124CA-7EDA-4a60-AEA9-7FB8D318B68F}" datafieldname="majorversionnumber" disabled="true" />
                </cell>
                <cell id="{6905b7b1-0eda-03b5-5216-09ae8b5d7a94}" showlabel="true" locklevel="0">
                    <labels>
                        <label description="Minor Version Number" languagecode="1033" />
                    </labels>
                    <control id="header_minorversionnumber" classid="{C6D124CA-7EDA-4a60-AEA9-7FB8D318B68F}" datafieldname="minorversionnumber" disabled="true" />
                </cell>
            </row>
        </rows>
    </footer>
    <events>
        <event name="onload" application="true" active="true">
            <InternalHandlers>
                <Handler functionName="KnowledgeManagement.KnowledgeArticle.Instance.form_onload" libraryName="msdyncrm_/KnowledgeManagement/KnowledgeArticle/KnowledgeArticleMainSystemLibrary.js" handlerUniqueId="32FE066C-23D0-4F34-A0FE-ABBC808C4DDD" enabled="true" passExecutionContext="true" />
                <Handler functionName="KnowledgeManagement.CommandBarActions.Instance.knowledgeArticle_onload" libraryName="msdyncrm_/KnowledgeManagementFeatureWebResource/KnowledgeArticleTemplate/KnowledgeArticleTemplateMainSystemLibrary.js" handlerUniqueId="527D720C-8C52-49ED-8199-965CC9F02752" enabled="true" passExecutionContext="true" />
            </InternalHandlers>
        </event>
        <event name="onsave" application="false" active="false">
            <InternalHandlers>
                <Handler functionName="KnowledgeManagement.KnowledgeArticle.Instance.form_onsave" libraryName="msdyncrm_/KnowledgeManagement/KnowledgeArticle/KnowledgeArticleMainSystemLibrary.js" handlerUniqueId="293220A9-B609-4EFE-9C94-0228E2603C94" enabled="true" passExecutionContext="true" />
            </InternalHandlers>
            <Handlers>
                <Handler functionName="KnowledgeArticleWorkOrderRelationship.OnSave" libraryName="msdyn_/KnowledgeArticle/KnowledgeArticleWorkOrderRelationship.js" handlerUniqueId="{277a3aa0-e3f6-47ef-bbf5-14d780c095cb}" enabled="true" parameters="" passExecutionContext="true" />
            </Handlers>
        </event>
        <event name="onchange" application="true" active="true" attribute="review">
            <InternalHandlers>
                <Handler functionName="KnowledgeManagement.KnowledgeArticle.Instance.review_onchange" libraryName="msdyncrm_/KnowledgeManagement/KnowledgeArticle/KnowledgeArticleMainSystemLibrary.js" handlerUniqueId="144c9ca5-f155-42f7-92c3-adaf74010dad" enabled="true" passExecutionContext="true" />
            </InternalHandlers>
        </event>
        <event name="onchange" application="true" active="true" attribute="expirationdate">
            <InternalHandlers>
                <Handler functionName="KnowledgeManagement.KnowledgeArticle.Instance.expirationdate_onchange" libraryName="msdyncrm_/KnowledgeManagement/KnowledgeArticle/KnowledgeArticleMainSystemLibrary.js" handlerUniqueId="a232c3bf-9a73-4112-be96-2d1096ea7cdf" enabled="true" passExecutionContext="true" />
            </InternalHandlers>
        </event>
        <event name="onchange" application="true" active="true" attribute="publishon">
            <InternalHandlers>
                <Handler functionName="KnowledgeManagement.KnowledgeArticle.Instance.publishdate_onchange" libraryName="msdyncrm_/KnowledgeManagement/KnowledgeArticle/KnowledgeArticleMainSystemLibrary.js" handlerUniqueId="a1e13678-163a-43dc-a24a-210c305682ab" enabled="true" passExecutionContext="true" />
            </InternalHandlers>
        </event>
        <event name="onchange" application="true" active="true" attribute="expiredreviewoptions">
            <InternalHandlers>
                <Handler functionName="KnowledgeManagement.KnowledgeArticle.Instance.expiredreviewoptions_onchange" libraryName="msdyncrm_/KnowledgeManagement/KnowledgeArticle/KnowledgeArticleMainSystemLibrary.js" handlerUniqueId="f4799561-c9c9-4b6d-9245-0e515cbb2067" enabled="true" passExecutionContext="true" />
            </InternalHandlers>
        </event>
    </events>
    <clientresources>
        <internalresources>
            <clientvariables />
            <clientincludes>
                <internaljscriptfile src="$webresource:msdyncrm_/KnowledgeManagement/KnowledgeArticle/KnowledgeArticleMainSystemLibrary.js" />
            </clientincludes>
        </internalresources>
    </clientresources>
    <controlDescriptions>
        <controlDescription forControl="{E7328698-05C1-7D5D-435C-754E27197E75}">
            <customControl formFactor="2" name="MscrmControls.KbEditorControl.KbEditorControl">
                <parameters>
                    <value>content</value>
                </parameters>
            </customControl>
            <customControl formFactor="0" name="MscrmControls.KbEditorControl.KbEditorControl">
                <parameters>
                    <value>content</value>
                </parameters>
            </customControl>
            <customControl formFactor="1" name="MscrmControls.KbEditorControl.KbEditorControl">
                <parameters>
                    <value>content</value>
                </parameters>
            </customControl>
        </controlDescription>
        <controlDescription forControl="{216CE061-1BD8-BE44-6786-B4EA9898527D}">
            <customControl id="{02D4264B-47E2-4B4C-AA95-F439F3F4D458}">
                <parameters />
            </customControl>
            <customControl formFactor="0" name="MscrmControls.Grid.ReadOnlyGrid">
                <parameters>
                    <data-set name="Grid">
                        <ViewId>{74AD0068-53AE-47A1-B98C-A7132FC9F91E}</ViewId>
                        <columnsDefaultView />
                        <IsUserView>false</IsUserView>
                        <RelationshipName>knowledgearticle_parentarticle_contentid</RelationshipName>
                        <TargetEntityType>knowledgearticle</TargetEntityType>
                        <EnableViewPicker>false</EnableViewPicker>
                        <FilteredViewIds />
                    </data-set>
                    <EnableGroupBy static="true" type="Enum">no</EnableGroupBy>
                    <CardForm static="true" type="Form.Card">77d76460-872e-42f3-9a9c-a2465f465409:Card|knowledgearticle|00000000-0000-0000-0000-000000000000</CardForm>
                    <EnableEditing static="true" type="Enum">no</EnableEditing>
                    <ReflowBehavior static="true" type="Enum">Reflow</ReflowBehavior>
                    <EnableFiltering static="true" type="Enum">no</EnableFiltering>
                </parameters>
            </customControl>
            <customControl formFactor="1" name="MscrmControls.Grid.ReadOnlyGrid">
                <parameters>
                    <data-set name="Grid">
                        <ViewId>{74AD0068-53AE-47A1-B98C-A7132FC9F91E}</ViewId>
                        <columnsDefaultView />
                        <IsUserView>false</IsUserView>
                        <RelationshipName>knowledgearticle_parentarticle_contentid</RelationshipName>
                        <TargetEntityType>knowledgearticle</TargetEntityType>
                        <EnableViewPicker>false</EnableViewPicker>
                        <FilteredViewIds />
                    </data-set>
                    <EnableGroupBy static="true" type="Enum">no</EnableGroupBy>
                    <CardForm static="true" type="Form.Card">77d76460-872e-42f3-9a9c-a2465f465409:Card|knowledgearticle|00000000-0000-0000-0000-000000000000</CardForm>
                    <EnableEditing static="true" type="Enum">no</EnableEditing>
                    <ReflowBehavior static="true" type="Enum">Reflow</ReflowBehavior>
                    <EnableFiltering static="true" type="Enum">no</EnableFiltering>
                </parameters>
            </customControl>
            <customControl formFactor="2" name="MscrmControls.Grid.ReadOnlyGrid">
                <parameters>
                    <data-set name="Grid">
                        <ViewId>{74AD0068-53AE-47A1-B98C-A7132FC9F91E}</ViewId>
                        <columnsDefaultView />
                        <IsUserView>false</IsUserView>
                        <RelationshipName>knowledgearticle_parentarticle_contentid</RelationshipName>
                        <TargetEntityType>knowledgearticle</TargetEntityType>
                        <EnableViewPicker>false</EnableViewPicker>
                        <FilteredViewIds />
                    </data-set>
                    <EnableGroupBy static="true" type="Enum">no</EnableGroupBy>
                    <CardForm static="true" type="Form.Card">77d76460-872e-42f3-9a9c-a2465f465409:Card|knowledgearticle|00000000-0000-0000-0000-000000000000</CardForm>
                    <EnableEditing static="true" type="Enum">no</EnableEditing>
                    <ReflowBehavior static="true" type="Enum">Reflow</ReflowBehavior>
                    <EnableFiltering static="true" type="Enum">no</EnableFiltering>
                </parameters>
            </customControl>
        </controlDescription>
    </controlDescriptions>
    <formLibraries>
        <Library name="msdyncrm_/KnowledgeManagementFeatureWebResource/KnowledgeArticleTemplate/KnowledgeArticleTemplateMainSystemLibrary.js" libraryUniqueId="{a4b5be8e-1575-0e5a-9114-aee5c0e3e9c1}" />
    </formLibraries>
    <Navigation>
        <NavBar />
        <NavBarAreas>
            <NavBarArea Id="Info">
                <Titles>
                    <Title LCID="1033" Text="Common" />
                    <Title LCID="1025" Text="" />
                    <Title LCID="1026" Text="" />
                    <Title LCID="1027" Text="Comuna" />
                    <Title LCID="1029" Text="Spolen" />
                    <Title LCID="1030" Text="Flles" />
                    <Title LCID="1031" Text="Allgemein" />
                    <Title LCID="1032" Text="" />
                    <Title LCID="3082" Text="Comn" />
                    <Title LCID="1061" Text="Levinud" />
                    <Title LCID="1069" Text="Ohikoa" />
                    <Title LCID="1035" Text="Yhteiset" />
                    <Title LCID="1036" Text="Commun" />
                    <Title LCID="1110" Text="Comn" />
                    <Title LCID="1037" Text="" />
                    <Title LCID="1081" Text="" />
                    <Title LCID="1050" Text="Zajedniko" />
                    <Title LCID="1038" Text="ltalnos" />
                    <Title LCID="1057" Text="Biasa" />
                    <Title LCID="1040" Text="Comune" />
                    <Title LCID="1041" Text="" />
                    <Title LCID="1087" Text="" />
                    <Title LCID="1042" Text="" />
                    <Title LCID="1063" Text="prasta" />
                    <Title LCID="1062" Text="Kopj informcija" />
                    <Title LCID="1086" Text="Lazim" />
                    <Title LCID="1044" Text="Felles" />
                    <Title LCID="1043" Text="Algemeen" />
                    <Title LCID="1045" Text="Wsplne" />
                    <Title LCID="1046" Text="Comum" />
                    <Title LCID="2070" Text="Comum" />
                    <Title LCID="1048" Text="Comun" />
                    <Title LCID="1049" Text="" />
                    <Title LCID="1051" Text="Spolon" />
                    <Title LCID="1060" Text="Splono" />
                    <Title LCID="3098" Text="" />
                    <Title LCID="2074" Text="Uobiajeno" />
                    <Title LCID="1053" Text="Allmnt" />
                    <Title LCID="1054" Text="" />
                    <Title LCID="1055" Text="Ortak" />
                    <Title LCID="1058" Text="" />
                    <Title LCID="1066" Text="Thng thng" />
                    <Title LCID="2052" Text="" />
                    <Title LCID="3076" Text="" />
                    <Title LCID="1028" Text="" />
                </Titles>
            </NavBarArea>
            <NavBarArea Id="Sales">
                <Titles>
                    <Title LCID="1033" Text="Sales" />
                    <Title LCID="1025" Text="" />
                    <Title LCID="1026" Text="" />
                    <Title LCID="1027" Text="Vendes" />
                    <Title LCID="1029" Text="Prodej" />
                    <Title LCID="1030" Text="Salg" />
                    <Title LCID="1031" Text="Vertrieb" />
                    <Title LCID="1032" Text="" />
                    <Title LCID="3082" Text="Ventas" />
                    <Title LCID="1061" Text="Mk" />
                    <Title LCID="1069" Text="Salmentak" />
                    <Title LCID="1035" Text="Myynti" />
                    <Title LCID="1036" Text="Ventes" />
                    <Title LCID="1110" Text="Vendas" />
                    <Title LCID="1037" Text="" />
                    <Title LCID="1081" Text="" />
                    <Title LCID="1050" Text="Prodaja" />
                    <Title LCID="1038" Text="rtkests" />
                    <Title LCID="1057" Text="Penjualan" />
                    <Title LCID="1040" Text="Vendite" />
                    <Title LCID="1041" Text="" />
                    <Title LCID="1087" Text="" />
                    <Title LCID="1042" Text="" />
                    <Title LCID="1063" Text="Pardavimas" />
                    <Title LCID="1062" Text="Prdoana" />
                    <Title LCID="1086" Text="Jualan" />
                    <Title LCID="1044" Text="Salg" />
                    <Title LCID="1043" Text="Verkoop" />
                    <Title LCID="1045" Text="Sprzeda" />
                    <Title LCID="1046" Text="Vendas" />
                    <Title LCID="2070" Text="Vendas" />
                    <Title LCID="1048" Text="Vnzri" />
                    <Title LCID="1049" Text="" />
                    <Title LCID="1051" Text="Predaj" />
                    <Title LCID="1060" Text="Prodaja" />
                    <Title LCID="3098" Text="" />
                    <Title LCID="2074" Text="Prodaja" />
                    <Title LCID="1053" Text="Frsljning" />
                    <Title LCID="1054" Text="" />
                    <Title LCID="1055" Text="Sat" />
                    <Title LCID="1058" Text="" />
                    <Title LCID="1066" Text="Bn hng" />
                    <Title LCID="2052" Text="" />
                    <Title LCID="3076" Text="" />
                    <Title LCID="1028" Text="" />
                </Titles>
            </NavBarArea>
            <NavBarArea Id="Service">
                <Titles>
                    <Title LCID="1033" Text="Service" />
                    <Title LCID="1025" Text="" />
                    <Title LCID="1026" Text="" />
                    <Title LCID="1027" Text="Servei" />
                    <Title LCID="1029" Text="Sluby" />
                    <Title LCID="1030" Text="Service" />
                    <Title LCID="1031" Text="Service" />
                    <Title LCID="1032" Text="" />
                    <Title LCID="3082" Text="Servicio" />
                    <Title LCID="1061" Text="Teenindus" />
                    <Title LCID="1069" Text="Zerbitzua" />
                    <Title LCID="1035" Text="Palvelu" />
                    <Title LCID="1036" Text="Service" />
                    <Title LCID="1110" Text="Servizo" />
                    <Title LCID="1037" Text="" />
                    <Title LCID="1081" Text="" />
                    <Title LCID="1050" Text="Usluga" />
                    <Title LCID="1038" Text="Szolgltats" />
                    <Title LCID="1057" Text="Layanan" />
                    <Title LCID="1040" Text="Servizio" />
                    <Title LCID="1041" Text="" />
                    <Title LCID="1087" Text="" />
                    <Title LCID="1042" Text="" />
                    <Title LCID="1063" Text="Tarnyba" />
                    <Title LCID="1062" Text="Serviss" />
                    <Title LCID="1086" Text="Perkhidmatan" />
                    <Title LCID="1044" Text="Service" />
                    <Title LCID="1043" Text="Service" />
                    <Title LCID="1045" Text="Usuga" />
                    <Title LCID="1046" Text="Servio" />
                    <Title LCID="2070" Text="Servio" />
                    <Title LCID="1048" Text="Serviciu" />
                    <Title LCID="1049" Text="" />
                    <Title LCID="1051" Text="Sluby" />
                    <Title LCID="1060" Text="Storitev" />
                    <Title LCID="3098" Text="" />
                    <Title LCID="2074" Text="Usluge" />
                    <Title LCID="1053" Text="Tjnst" />
                    <Title LCID="1054" Text="" />
                    <Title LCID="1055" Text="Servis" />
                    <Title LCID="1058" Text="" />
                    <Title LCID="1066" Text="Dch v" />
                    <Title LCID="2052" Text="" />
                    <Title LCID="3076" Text="" />
                    <Title LCID="1028" Text="" />
                </Titles>
            </NavBarArea>
            <NavBarArea Id="Marketing">
                <Titles>
                    <Title LCID="1033" Text="Marketing" />
                    <Title LCID="1025" Text="" />
                    <Title LCID="1026" Text="" />
                    <Title LCID="1027" Text="Mrqueting" />
                    <Title LCID="1029" Text="Marketing" />
                    <Title LCID="1030" Text="Marketing" />
                    <Title LCID="1031" Text="Marketing" />
                    <Title LCID="1032" Text="" />
                    <Title LCID="3082" Text="Marketing" />
                    <Title LCID="1061" Text="Turundus" />
                    <Title LCID="1069" Text="Marketina" />
                    <Title LCID="1035" Text="Markkinointi" />
                    <Title LCID="1036" Text="Marketing" />
                    <Title LCID="1110" Text="Mrketing" />
                    <Title LCID="1037" Text="" />
                    <Title LCID="1081" Text="" />
                    <Title LCID="1050" Text="Marketing" />
                    <Title LCID="1038" Text="Marketing" />
                    <Title LCID="1057" Text="Pemasaran" />
                    <Title LCID="1040" Text="Marketing" />
                    <Title LCID="1041" Text="" />
                    <Title LCID="1087" Text="" />
                    <Title LCID="1042" Text="" />
                    <Title LCID="1063" Text="Rinkodara" />
                    <Title LCID="1062" Text="Mrketings" />
                    <Title LCID="1086" Text="Pemasaran" />
                    <Title LCID="1044" Text="Markedsfring" />
                    <Title LCID="1043" Text="Marketing" />
                    <Title LCID="1045" Text="Marketing" />
                    <Title LCID="1046" Text="Marketing" />
                    <Title LCID="2070" Text="Marketing" />
                    <Title LCID="1048" Text="Marketing" />
                    <Title LCID="1049" Text="" />
                    <Title LCID="1051" Text="Marketing" />
                    <Title LCID="1060" Text="Trenje" />
                    <Title LCID="3098" Text="" />
                    <Title LCID="2074" Text="Marketing" />
                    <Title LCID="1053" Text="Marknadsfring" />
                    <Title LCID="1054" Text="" />
                    <Title LCID="1055" Text="Pazarlama" />
                    <Title LCID="1058" Text="" />
                    <Title LCID="1066" Text="Tip th" />
                    <Title LCID="2052" Text="" />
                    <Title LCID="3076" Text="" />
                    <Title LCID="1028" Text="" />
                </Titles>
            </NavBarArea>
            <NavBarArea Id="ProcessCenter">
                <Titles>
                    <Title LCID="1033" Text="Process Sessions" />
                    <Title LCID="1025" Text="  " />
                    <Title LCID="1026" Text="  " />
                    <Title LCID="1027" Text="Sessions del procs" />
                    <Title LCID="1029" Text="Relace proces" />
                    <Title LCID="1030" Text="Processessioner" />
                    <Title LCID="1031" Text="Prozesssitzungen" />
                    <Title LCID="1032" Text="  " />
                    <Title LCID="3082" Text="Sesiones de proceso" />
                    <Title LCID="1061" Text="Protsessiseansid" />
                    <Title LCID="1069" Text="Prozesu-saioak" />
                    <Title LCID="1035" Text="Prosessin istunnot" />
                    <Title LCID="1036" Text="Sessions de traitement" />
                    <Title LCID="1110" Text="Sesins de proceso" />
                    <Title LCID="1037" Text=" " />
                    <Title LCID="1081" Text=" " />
                    <Title LCID="1050" Text="Sesije procesa" />
                    <Title LCID="1038" Text="Feldolgozsi munkamenetek" />
                    <Title LCID="1057" Text="Sesi Proses" />
                    <Title LCID="1040" Text="Sessioni processo" />
                    <Title LCID="1041" Text=" " />
                    <Title LCID="1087" Text=" " />
                    <Title LCID="1042" Text=" " />
                    <Title LCID="1063" Text="Apdorojimo seansai" />
                    <Title LCID="1062" Text="Apstrdes sesijas" />
                    <Title LCID="1086" Text="Sesi Proses" />
                    <Title LCID="1044" Text="Prosesskter" />
                    <Title LCID="1043" Text="Sessies verwerken" />
                    <Title LCID="1045" Text="Sesje procesw" />
                    <Title LCID="1046" Text="Sesses do Processo" />
                    <Title LCID="2070" Text="Sesses de Processamento" />
                    <Title LCID="1048" Text="Sesiuni de proces" />
                    <Title LCID="1049" Text=" " />
                    <Title LCID="1051" Text="Relcie procesov" />
                    <Title LCID="1060" Text="Seje obdelave" />
                    <Title LCID="3098" Text=" " />
                    <Title LCID="2074" Text="Sesije procesa" />
                    <Title LCID="1053" Text="Bearbetningssessioner" />
                    <Title LCID="1054" Text="" />
                    <Title LCID="1055" Text="lem Oturumlar" />
                    <Title LCID="1058" Text=" " />
                    <Title LCID="1066" Text="Phin Quy trnh" />
                    <Title LCID="2052" Text="" />
                    <Title LCID="3076" Text="" />
                    <Title LCID="1028" Text="" />
                </Titles>
            </NavBarArea>
        </NavBarAreas>
    </Navigation>
    <formparameters>
        <querystringparameter name="param_msdyn_workorderid" type="SafeString" />
    </formparameters>
    <DisplayConditions Order="0" FallbackForm="true">
        <Everyone />
    </DisplayConditions>
</form>